fastrestapi/__init__.py
fastrestapi/app/app.py
fastrestapi-0.0.3.dist-info/WHEEL
fastrestapi-0.0.3.dist-info/METADATA
fastrestapi-0.0.3.dist-info/RECORD
